{
  "slugKey": "vpk-60c",
  "published": true,
  "slug": {
    "ru": "vpk-60c",
    "en": "vpk-60c"
  },
  "title": {
    "ru": "Покрытие ВПК-60Ц",
    "en": "VPK-60C"
  },
  "excerpt": {
    "ru": "Покрытие ВПК-60Ц — продукт категории «Противопригарные покрытия» для литейного производства. процессы: ПГС; основа: Водное",
    "en": "VPK-60C is part of the \"Противопригарные покрытия\" line for foundry workflows. processes: ПГС; base: Водное"
  },
  "content": {},
  "category": "Противопригарные покрытия",
  "process": [
    "ПГС"
  ],
  "base": [
    "Водное"
  ],
  "filler": [],
  "metals": [],
  "auxiliary": [],
  "updatedAt": "2025-11-27T15:22"
}
